bemyai/__init__.py
bemyai/__main__.py
bemyai/langs.py
bemyai/schema.py
bemyai-1.0.1.dist-info/METADATA
bemyai-1.0.1.dist-info/WHEEL
bemyai-1.0.1.dist-info/entry_points.txt
bemyai-1.0.1.dist-info/RECORD
