Metadata-Version: 2.4
Name: bemyai
Version: 1.0.1
Summary: Be My AI API
Author-email: Alexey <aleks-samos@yandex.ru>
Requires-Python: >3.8.0
Requires-Dist: aiofiles<24,>=23.2.1
Requires-Dist: aiohttp<4,>=3.9.1
Requires-Dist: loguru<0.8,>=0.7.2
Requires-Dist: pillow<11,>=10.2.0
Requires-Dist: pydantic<3,>=2.5.3
